Metadata-Version: 2.1
Name: fastapi-fixed
Version: 0.105.3
Summary: FastAPI framework, high performance, easy to learn, fast to code, ready for production
Project-URL: Homepage, https://github.com/tiangolo/fastapi
Project-URL: Documentation, https://fastapi.tiangolo.com/
Project-URL: Repository, https://github.com/tiangolo/fastapi
Author: test
License-Expression: MIT
License-File: LICENSE
Classifier: Development Status :: 4 - Beta
Classifier: Environment :: Web Environment
Classifier: Framework :: AsyncIO
Classifier: Framework :: FastAPI
Classifier: Framework :: Pydantic
Classifier: Framework :: Pydantic :: 1
Classifier: Intended Audience :: Developers
Classifier: Intended Audience :: Information Technology
Classifier: Intended Audience :: System Administrators
Classifier: License :: OSI Approved :: MIT License
Classifier: Operating System :: OS Independent
Classifier: Programming Language :: Python
Classifier: Programming Language :: Python :: 3
Classifier: Programming Language :: Python :: 3 :: Only
Classifier: Programming Language :: Python :: 3.8
Classifier: Programming Language :: Python :: 3.9
Classifier: Programming Language :: Python :: 3.10
Classifier: Programming Language :: Python :: 3.11
Classifier: Topic :: Internet
Classifier: Topic :: Internet :: WWW/HTTP
Classifier: Topic :: Internet :: WWW/HTTP :: HTTP Servers
Classifier: Topic :: Software Development
Classifier: Topic :: Software Development :: Libraries
Classifier: Topic :: Software Development :: Libraries :: Application Frameworks
Classifier: Topic :: Software Development :: Libraries :: Python Modules
Classifier: Typing :: Typed
Requires-Python: >=3.8
Requires-Dist: anyio<4.0.0,>=3.7.1
Requires-Dist: pydantic!=1.8,!=1.8.1,!=2.0.0,!=2.0.1,!=2.1.0,<3.0.0,>=1.7.4
Requires-Dist: starlette<0.28.0,>=0.27.0
Requires-Dist: typing-extensions>=4.8.0
Provides-Extra: all
Requires-Dist: email-validator>=2.0.0; extra == 'all'
Requires-Dist: httpx>=0.23.0; extra == 'all'
Requires-Dist: itsdangerous>=1.1.0; extra == 'all'
Requires-Dist: jinja2>=2.11.2; extra == 'all'
Requires-Dist: orjson>=3.2.1; extra == 'all'
Requires-Dist: pydantic-extra-types>=2.0.0; extra == 'all'
Requires-Dist: pydantic-settings>=2.0.0; extra == 'all'
Requires-Dist: python-multipart>=0.0.5; extra == 'all'
Requires-Dist: pyyaml>=5.3.1; extra == 'all'
Requires-Dist: ujson!=4.0.2,!=4.1.0,!=4.2.0,!=4.3.0,!=5.0.0,!=5.1.0,>=4.0.1; extra == 'all'
Requires-Dist: uvicorn[standard]>=0.12.0; extra == 'all'
